adnus/__init__.py
adnus/_version.py
adnus/main.py
adnus-0.2.2.dist-info/licenses/LICENSE
adnus-0.2.2.dist-info/METADATA
adnus-0.2.2.dist-info/WHEEL
adnus-0.2.2.dist-info/top_level.txt
adnus-0.2.2.dist-info/RECORD
