Metadata-Version: 2.4
Name: adnus
Version: 0.2.2
Summary: A Python library for Advanced Number Systems (AdNuS), including Bicomplex, Neutrosophic, Hyperreal numbers, reals, Complex, Quaternion, Octonion, Sedenion, Pathion, Chingon, Routon, Voudon.
Home-page: https://github.com/WhiteSymmetry/adnus
Author: Mehmet Keçeci
Author-email: Mehmet Keçeci <mkececi@yaani.com>
Maintainer: Mehmet Keçeci
Maintainer-email: Mehmet Keçeci <mkececi@yaani.com>
License:                     GNU AFFERO GENERAL PUBLIC LICENSE
Classifier: Programming Language :: Python :: 3
Classifier: Operating System :: OS Independent
Classifier: Intended Audience :: Science/Research
Classifier: Topic :: Scientific/Engineering :: Visualization
Requires-Python: >=3.11
License-File: LICENSE
Requires-Dist: numpy>=2.4.1
Provides-Extra: dev
Requires-Dist: pytest>=9.0.2; extra == "dev"
Provides-Extra: build
Requires-Dist: setuptools>=80.10.1; extra == "build"
Requires-Dist: cython>=3.2.4; extra == "build"
Dynamic: author
Dynamic: home-page
Dynamic: license-file
Dynamic: maintainer
Dynamic: requires-python
